README.md
setup.py
qth_alias/__init__.py
qth_alias/alias.py
qth_alias/server.py
qth_alias/version.py
qth_alias.egg-info/PKG-INFO
qth_alias.egg-info/SOURCES.txt
qth_alias.egg-info/dependency_links.txt
qth_alias.egg-info/entry_points.txt
qth_alias.egg-info/requires.txt
qth_alias.egg-info/top_level.txt