Metadata-Version: 1.1
Name: qth-alias
Version: 0.1.2
Summary: Utility for creating aliases of Qth properties and events.
Home-page: https://github.com/mossblaser/qth_alias
Author: Jonathan Heathcote
Author-email: UNKNOWN
License: GPLv2
Keywords: mqtt asyncio home-automation messaging
Platform: UNKNOWN
Classifier: Development Status :: 3 - Alpha
Classifier: Intended Audience :: Developers
Classifier: License :: OSI Approved :: GNU General Public License v2 (GPLv2)
Classifier: Operating System :: POSIX :: Linux
Classifier: Operating System :: Microsoft :: Windows
Classifier: Operating System :: MacOS
Classifier: Programming Language :: Python :: 3
Classifier: Programming Language :: Python :: 3.4
Classifier: Programming Language :: Python :: 3.5
